mlprofiler/pywrap/_pywrap_profiler_plugin.pyi
tensorboard_plugin_profile/__init__.py
tensorboard_plugin_profile/profile_plugin.py
tensorboard_plugin_profile/profile_plugin_loader.py
tensorboard_plugin_profile/version.py
tensorboard_plugin_profile/convert/dcn_collective_stats_proto_to_gviz.py
tensorboard_plugin_profile/convert/diagnostics.py
tensorboard_plugin_profile/convert/inference_stats_proto_to_gviz.py
tensorboard_plugin_profile/convert/input_pipeline_proto_to_gviz.py
tensorboard_plugin_profile/convert/kernel_stats_proto_to_gviz.py
tensorboard_plugin_profile/convert/overview_page_proto_to_gviz.py
tensorboard_plugin_profile/convert/raw_to_tool_data.py
tensorboard_plugin_profile/convert/roofline_model_proto_to_gviz.py
tensorboard_plugin_profile/convert/tf_data_stats_proto_to_gviz.py
tensorboard_plugin_profile/convert/tf_stats_proto_to_gviz.py
tensorboard_plugin_profile/convert/trace_events_json.py
tensorboard_plugin_profile/integration_tests/tf_mnist.py
tensorboard_plugin_profile/integration_tests/tf_profiler_session.py
tensorboard_plugin_profile/integration_tests/tpu/tensorflow/tpu_tf2_keras_test.py
tensorboard_plugin_profile/protobuf/dcn_slack_analysis_pb2.py
tensorboard_plugin_profile/protobuf/diagnostics_pb2.py
tensorboard_plugin_profile/protobuf/hlo_stats_pb2.py
tensorboard_plugin_profile/protobuf/inference_stats_pb2.py
tensorboard_plugin_profile/protobuf/input_pipeline_pb2.py
tensorboard_plugin_profile/protobuf/kernel_stats_pb2.py
tensorboard_plugin_profile/protobuf/overview_page_pb2.py
tensorboard_plugin_profile/protobuf/power_metrics_pb2.py
tensorboard_plugin_profile/protobuf/roofline_model_pb2.py
tensorboard_plugin_profile/protobuf/tf_data_stats_pb2.py
tensorboard_plugin_profile/protobuf/tf_stats_pb2.py
tensorboard_plugin_profile/protobuf/tpu_input_pipeline_pb2.py
tensorboard_plugin_profile/protobuf/trace_events_pb2.py
tensorboard_plugin_profile/static/bundle.js
tensorboard_plugin_profile/static/index.html
tensorboard_plugin_profile/static/index.js
tbp_testing-2.19.0.dist-info/METADATA
tbp_testing-2.19.0.dist-info/WHEEL
tbp_testing-2.19.0.dist-info/entry_points.txt
tbp_testing-2.19.0.dist-info/top_level.txt
tbp_testing-2.19.0.dist-info/RECORD
